README
setup.py
negspy/__init__.py
negspy/coordinates.py
negspy.egg-info/PKG-INFO
negspy.egg-info/SOURCES.txt
negspy.egg-info/dependency_links.txt
negspy.egg-info/top_level.txt
negspy/data/GCA_000001215.4_Release_6_plus_ISO1_MT_genomic/chromInfo.txt
negspy/data/GCA_000001405.15_GRCh38_genomic/chromInfo.txt
negspy/data/GCF_000005845.2_ASM584v2_genomic/chromInfo.txt
negspy/data/b37/chromInfo.txt
negspy/data/b37/chromOrder.txt
negspy/data/canFam3/chromInfo.txt
negspy/data/ce11/chromInfo.txt
negspy/data/danRer10/chromInfo.txt
negspy/data/dm3/chromInfo.txt
negspy/data/dm3/chromOrder.txt
negspy/data/dm6/chromInfo.txt
negspy/data/galGal5/chromInfo.txt
negspy/data/galGal6/chromInfo.txt
negspy/data/gorGor5/chromInfo.txt
negspy/data/grch37/chromInfo.txt
negspy/data/grch37/chromOrder.txt
negspy/data/grch37-lite/chromInfo.txt
negspy/data/h37rv/chromInfo.txt
negspy/data/hg19/chromInfo.txt
negspy/data/hg38/chromInfo.txt
negspy/data/hs37d5/chromInfo.txt
negspy/data/mm10/chromInfo.txt
negspy/data/mm9/chromInfo.txt
negspy/data/mm9/chromOrder.txt
negspy/data/mm9b/chromInfo.txt
negspy/data/panTro5/chromInfo.txt
negspy/data/rheMac8/chromInfo.txt
negspy/data/rn6/chromInfo.txt
negspy/data/sacCer3/chromInfo.txt
negspy/data/test/chromInfo.txt
negspy/data/test3chroms/chromInfo.txt
negspy/data/test3chroms/chromOrder.txt
scripts/chr_pos_to_genome_pos.py
scripts/create_chrominfo.py
scripts/make_triangular.py