Metadata-Version: 1.0
Name: negspy
Version: 0.2.24
Summary: Python NGS tools
Home-page: UNKNOWN
Author: Peter Kerpedjiev
Author-email: pkerpedjiev@gmail.com
License: UNKNOWN
Platform: UNKNOWN
